History.txt
LICENCE.txt
MANIFEST.in
README.rst
To_Do.txt
setup.cfg
setup.py
pyswath/DEMswath2.png
pyswath/__init__.py
pyswath/_version.py
pyswath/checks.py
pyswath/plotgraph.py
pyswath/profiles.py
pyswath/raster_tools.py
pyswath/swath.py
pyswath.egg-info/PKG-INFO
pyswath.egg-info/SOURCES.txt
pyswath.egg-info/dependency_links.txt
pyswath.egg-info/not-zip-safe
pyswath.egg-info/requires.txt
pyswath.egg-info/top_level.txt