Metadata-Version: 1.1
Name: pyswath
Version: 2.0.4
Summary: package that provide tools to extract swath profiles from a raster map
Home-page: https://github.com/robertxa/pyswath
Author: Xavier Robert
Author-email: xavier.robert@univ-grenoble-alpes.fr
License: GPL-V3.0
Download-URL: https://github.com/robertxa/pyswath/archive/master.zip
Platform: UNKNOWN
Classifier: Operating System :: OS Independent
Classifier: Topic :: Scientific/Engineering :: GIS
